eve_client/__init__.py
eve_client/__version__.py
eve_client/eve.py
eve_client/helper.py
eve_client-2.0.16.dist-info/LICENSE.md
eve_client-2.0.16.dist-info/METADATA
eve_client-2.0.16.dist-info/WHEEL
eve_client-2.0.16.dist-info/RECORD
