Metadata-Version: 2.1
Name: eve-client
Version: 2.0.16
Summary: EVE Client API Library from Exodus Intelligence LLC.
License: BSD-3-Clause
Author: DevTeam
Author-email: dev@exodusintel.com
Requires-Python: >=3.8,<4.0
Classifier: License :: OSI Approved :: BSD License
Classifier: Programming Language :: Python :: 3
Classifier: Programming Language :: Python :: 3.8
Classifier: Programming Language :: Python :: 3.9
Classifier: Programming Language :: Python :: 3.10
Classifier: Programming Language :: Python :: 3.11
Requires-Dist: PyNaCl (==1.4.0)
Requires-Dist: python-dateutil (==2.8.2)
Requires-Dist: requests (>=2.26.0,<3.0.0)
